LICENSE
README.md
setup.py
blockchaintools/__init__.py
blockchaintools/blockchain.py
python_blockchaintools.egg-info/PKG-INFO
python_blockchaintools.egg-info/SOURCES.txt
python_blockchaintools.egg-info/dependency_links.txt
python_blockchaintools.egg-info/requires.txt
python_blockchaintools.egg-info/top_level.txt