Metadata-Version: 2.1
Name: python-blockchaintools
Version: 1.0.0
Summary: python blockchain tools
Home-page: https://github.com/xuguox/blockchain-tools
Author: neason
Author-email: xgx93610@gmail.com
License: MIT
Project-URL: Source, https://github.com/xuguox/blockchain-tools
Classifier: Programming Language :: Python :: 3
Classifier: License :: OSI Approved :: MIT License
Classifier: Operating System :: OS Independent
Requires-Python: >=3.7.0
License-File: LICENSE
Requires-Dist: requests
Requires-Dist: python-positiontools
Requires-Dist: python-timetools
